treedist.py
treedist-1.0.1.dist-info/LICENSE
treedist-1.0.1.dist-info/METADATA
treedist-1.0.1.dist-info/WHEEL
treedist-1.0.1.dist-info/entry_points.txt
treedist-1.0.1.dist-info/top_level.txt
treedist-1.0.1.dist-info/RECORD
