Metadata-Version: 2.1
Name: treedist
Version: 1.0.1
Summary: Computes measures of (dis)similarity between phylogenetic trees. Provides summaries of shared and unique bipartitions.
Home-page: https://github.com/agormp/treedist
Author: Anders Gorm Pedersen
Author-email: agpe@dtu.dk
Classifier: Programming Language :: Python :: 3
Classifier: License :: OSI Approved :: GNU General Public License v3 (GPLv3)
Classifier: Operating System :: OS Independent
Requires-Python: >=3.6
License-File: LICENSE
Requires-Dist: phylotreelib
